diltsobot/__init__.py
diltsobot/main.py
diltsobot/cogs/core.py
diltsobot/cogs/defs.py
diltsobot/cogs/lockdown.py
diltsobot/cogs/managment.py
diltsobot/cogs/mass.py
diltsobot-7.dist-info/LICENCE
diltsobot-7.dist-info/METADATA
diltsobot-7.dist-info/WHEEL
diltsobot-7.dist-info/top_level.txt
diltsobot-7.dist-info/RECORD
