Metadata-Version: 2.1
Name: diltsobot
Version: 7
Summary: Personal project ig
Home-page: https://github.com/mariohero24/diltsobot
Author: Guard Boi
Author-email: guard@cowbot.xyz
Classifier: Programming Language :: Python :: 3
Classifier: License :: OSI Approved :: MIT License
Classifier: Operating System :: OS Independent
Requires-Python: >=3.10.6
License-File: LICENCE
